LICENSE
gibbon/__init__.py
gibbon/__main__.py
gibbon/tree.py
gibbon/types.py
gibbon/util.py
gibbon-0.1.3.dist-info/entry_points.txt
gibbon-0.1.3.dist-info/LICENSE
gibbon-0.1.3.dist-info/WHEEL
gibbon-0.1.3.dist-info/METADATA
gibbon-0.1.3.dist-info/RECORD
