Metadata-Version: 2.1
Name: gibbon
Version: 0.1.3
Summary: 
Home-page: https://github.com/dawsonbooth/gibbon
License: MIT
Author: Dawson Booth
Author-email: pypi@dawsonbooth.com
Requires-Python: >=3.7,<4.0
Classifier: Environment :: Console
Classifier: License :: OSI Approved :: MIT License
Classifier: Operating System :: OS Independent
Classifier: Programming Language :: Python :: 3
Classifier: Programming Language :: Python :: 3.7
Classifier: Programming Language :: Python :: 3.8
Classifier: Programming Language :: Python :: 3.9
Requires-Dist: tqdm (>=4.59.0,<5.0.0)
Project-URL: Documentation, https://dawsonbooth.github.io/gibbon
Project-URL: Repository, https://github.com/dawsonbooth/gibbon
